[
    {
        "publisher": "timonwong",
        "name": "shellcheck",
        "version": "0.32.5",
        "src": {
            "name": "timonwong-shellcheck-0.32.5.zip",
            "platforms": {
                "x86_64-linux": {
                    "url": "https://timonwong.gallerycdn.vsassets.io/extensions/timonwong/shellcheck/0.32.5/1682390178439/Microsoft.VisualStudio.Services.VSIXPackage",
                    "sha256": "sha256-F77exPlyBX99tkKADbfAIbktF+9K+I1LHhVrO5wS2Qs="
                },
                "aarch64-darwin": {
                    "url": "https://timonwong.gallerycdn.vsassets.io/extensions/timonwong/shellcheck/0.32.5/1682390192219/Microsoft.VisualStudio.Services.VSIXPackage",
                    "sha256": "sha256-sn0vknrsxmeAF1nIIWdf/laINGefAej+ytsQbzFuaz4="
                },
                "aarch64-linux": {
                    "url": "https://timonwong.gallerycdn.vsassets.io/extensions/timonwong/shellcheck/0.32.5/1682390185118/Microsoft.VisualStudio.Services.VSIXPackage",
                    "sha256": "sha256-p8f9msBE78uG00D7TDD9Wv2O9h1yiQ1Bxv1x04QXil8="
                },
                "x86_64-darwin": {
                    "url": "https://timonwong.gallerycdn.vsassets.io/extensions/timonwong/shellcheck/0.32.5/1682390188281/Microsoft.VisualStudio.Services.VSIXPackage",
                    "sha256": "sha256-oe/4pJW4pH/DTypbwxOfdEdw7hCA1Ke7HTbuGp+FtwQ="
                }
            }
        }
    },
    {
        "publisher": "tamasfe",
        "name": "even-better-toml",
        "version": "0.19.0",
        "src": {
            "name": "tamasfe-even-better-toml-0.19.0.zip",
            "url": "https://tamasfe.gallerycdn.vsassets.io/extensions/tamasfe/even-better-toml/0.19.0/1667317056512/Microsoft.VisualStudio.Services.VSIXPackage",
            "sha256": "sha256-MqSQarNThbEf1wHDTf1yA46JMhWJN46b08c7tV6+1nU="
        }
    },
    {
        "publisher": "trond-snekvik",
        "name": "simple-rst",
        "version": "1.5.3",
        "src": {
            "name": "trond-snekvik-simple-rst-1.5.3.zip",
            "url": "https://trond-snekvik.gallerycdn.vsassets.io/extensions/trond-snekvik/simple-rst/1.5.3/1681639232785/Microsoft.VisualStudio.Services.VSIXPackage",
            "sha256": "sha256-0gPqckwzDptpzzg1tP4I9WQfrXlflO+G0KcAK5pEie8="
        }
    },
    {
        "publisher": "gruntfuggly",
        "name": "todo-tree",
        "version": "0.0.226",
        "src": {
            "name": "gruntfuggly-todo-tree-0.0.226.zip",
            "url": "https://gruntfuggly.gallerycdn.vsassets.io/extensions/gruntfuggly/todo-tree/0.0.226/1681324794296/Microsoft.VisualStudio.Services.VSIXPackage",
            "sha256": "sha256-Fj9cw+VJ2jkTGUclB1TLvURhzQsaryFQs/+f2RZOLHs="
        }
    },
    {
        "publisher": "vscodevim",
        "name": "vim",
        "version": "1.25.2",
        "src": {
            "name": "vscodevim-vim-1.25.2.zip",
            "url": "https://vscodevim.gallerycdn.vsassets.io/extensions/vscodevim/vim/1.25.2/1677732062761/Microsoft.VisualStudio.Services.VSIXPackage",
            "sha256": "sha256-hy2Ks6oRc9io6vfgql9aFGjUiRzBCS4mGdDO3NqIFEg="
        }
    },
    {
        "publisher": "bbenoist",
        "name": "nix",
        "version": "1.0.1",
        "src": {
            "name": "bbenoist-nix-1.0.1.zip",
            "url": "https://bbenoist.gallerycdn.vsassets.io/extensions/bbenoist/nix/1.0.1/1474455192924/Microsoft.VisualStudio.Services.VSIXPackage",
            "sha256": "sha256-qwxqOGublQeVP2qrLF94ndX/Be9oZOn+ZMCFX1yyoH0="
        }
    },
    {
        "publisher": "rust-lang",
        "name": "rust-analyzer",
        "version": "0.4.1505",
        "src": {
            "name": "rust-lang-rust-analyzer-0.4.1505.zip",
            "platforms": {
                "aarch64-linux": {
                    "url": "https://rust-lang.gallerycdn.vsassets.io/extensions/rust-lang/rust-analyzer/0.4.1505/1683506300809/Microsoft.VisualStudio.Services.VSIXPackage",
                    "sha256": "sha256-SduhmnPPhuXuZc0XSE5j/rQMXzMjeXw/z+/l6rUM/ZE="
                },
                "x86_64-linux": {
                    "url": "https://rust-lang.gallerycdn.vsassets.io/extensions/rust-lang/rust-analyzer/0.4.1505/1683506314020/Microsoft.VisualStudio.Services.VSIXPackage",
                    "sha256": "sha256-KuKaYrsF/fyVbBIGLqPuQO3awz++BvjQVdea7UjzXaI="
                },
                "aarch64-darwin": {
                    "url": "https://rust-lang.gallerycdn.vsassets.io/extensions/rust-lang/rust-analyzer/0.4.1505/1683506291903/Microsoft.VisualStudio.Services.VSIXPackage",
                    "sha256": "sha256-yMwK7QidS4Ctnwg7Oau11qF2TpHqRn/omHxrRhNdIwU="
                },
                "x86_64-darwin": {
                    "url": "https://rust-lang.gallerycdn.vsassets.io/extensions/rust-lang/rust-analyzer/0.4.1505/1683506296519/Microsoft.VisualStudio.Services.VSIXPackage",
                    "sha256": "sha256-d+uF9GmADv0w0WtUPzFRiWhvGFj/n6XStat9TMv/0yY="
                }
            }
        }
    },
    {
        "publisher": "ms-vscode-remote",
        "name": "remote-ssh",
        "version": "0.101.2023050515",
        "src": {
            "name": "ms-vscode-remote-remote-ssh-0.101.2023050515.zip",
            "url": "https://ms-vscode-remote.gallerycdn.vsassets.io/extensions/ms-vscode-remote/remote-ssh/0.101.2023050515/1683299181532/Microsoft.VisualStudio.Services.VSIXPackage",
            "sha256": "sha256-o+JowlbR/sELkf3QGvZW0MH3bsAJBneEDBq2G+iluwc="
        }
    }
]